CHANGES.md
LICENSE
MANIFEST.in
README.md
setup.py
blumycelium/__init__.py
blumycelium/_version.py
blumycelium/custom_types.py
blumycelium/graph_parameters.py
blumycelium/machine_elf.py
blumycelium/models.py
blumycelium/mycelium.py
blumycelium/the_exceptions.py
blumycelium/utils.py
blumycelium.egg-info/PKG-INFO
blumycelium.egg-info/SOURCES.txt
blumycelium.egg-info/dependency_links.txt
blumycelium.egg-info/entry_points.txt
blumycelium.egg-info/not-zip-safe
blumycelium.egg-info/requires.txt
blumycelium.egg-info/top_level.txt