Metadata-Version: 1.1
Name: blumycelium
Version: 0.1.0
Summary: blumycelium
Home-page: UNKNOWN
Author: Tariq Daouda
Author-email: UNKNOWN
License: UNKNOWN
Keywords: arangodb multithread bluwr multiprocessing async
Platform: UNKNOWN
Classifier: Programming Language :: Python
